README.rst
requirements.txt
setup.py
wptrunner.default.ini
test/test.py
wptrunner/__init__.py
wptrunner/config.json
wptrunner/config.py
wptrunner/environment.py
wptrunner/expected.py
wptrunner/hosts.py
wptrunner/manifestexpected.py
wptrunner/manifestinclude.py
wptrunner/manifestupdate.py
wptrunner/metadata.py
wptrunner/products.py
wptrunner/reduce.py
wptrunner/testharness_runner.html
wptrunner/testharnessreport-servo.js
wptrunner/testharnessreport.js
wptrunner/testloader.py
wptrunner/testrunner.py
wptrunner/vcs.py
wptrunner/wptcommandline.py
wptrunner/wptlogging.py
wptrunner/wptrunner.py
wptrunner/wpttest.py
wptrunner.egg-info/PKG-INFO
wptrunner.egg-info/SOURCES.txt
wptrunner.egg-info/dependency_links.txt
wptrunner.egg-info/entry_points.txt
wptrunner.egg-info/not-zip-safe
wptrunner.egg-info/requires.txt
wptrunner.egg-info/top_level.txt
wptrunner/browsers/__init__.py
wptrunner/browsers/b2g.py
wptrunner/browsers/base.py
wptrunner/browsers/chrome.py
wptrunner/browsers/firefox.py
wptrunner/browsers/server-locations.txt
wptrunner/browsers/servo.py
wptrunner/browsers/webdriver.py
wptrunner/browsers/b2g_setup/certtest_app.zip
wptrunner/executors/__init__.py
wptrunner/executors/base.py
wptrunner/executors/executormarionette.py
wptrunner/executors/executorselenium.py
wptrunner/executors/executorservo.py
wptrunner/executors/process.py
wptrunner/executors/reftest-wait.js
wptrunner/executors/reftest.js
wptrunner/executors/testharness_marionette.js
wptrunner/executors/testharness_webdriver.js
wptrunner/tests/__init__.py
wptrunner/tests/test_chunker.py
wptrunner/tests/test_hosts.py
wptrunner/tests/test_update.py
wptrunner/update/__init__.py
wptrunner/update/base.py
wptrunner/update/metadata.py
wptrunner/update/state.py
wptrunner/update/sync.py
wptrunner/update/tree.py
wptrunner/update/update.py
wptrunner/wptmanifest/__init__.py
wptrunner/wptmanifest/node.py
wptrunner/wptmanifest/parser.py
wptrunner/wptmanifest/serializer.py
wptrunner/wptmanifest/backends/__init__.py
wptrunner/wptmanifest/backends/conditional.py
wptrunner/wptmanifest/backends/static.py
wptrunner/wptmanifest/tests/__init__.py
wptrunner/wptmanifest/tests/test_conditional.py
wptrunner/wptmanifest/tests/test_parser.py
