Metadata-Version: 1.1
Name: wptrunner
Version: 1.14
Summary: Harness for running the W3C web-platform-tests against various products
Home-page: UNKNOWN
Author: Mozilla Automation and Testing Team
Author-email: tools@lists.mozilla.org
License: MPL 2.0
Platform: Any
Classifier: Development Status :: 4 - Beta
Classifier: Environment :: Console
Classifier: Intended Audience :: Developers
Classifier: License :: OSI Approved :: Mozilla Public License 2.0 (MPL 2.0)
Classifier: Operating System :: OS Independent
